{
  "name": "MySQL Dev Container",
  "features": {
    "ghcr.io/devcontainers/features/common-utils:1": {},
    "ghcr.io/devcontainers/features/mysql:1": {
      "version": "8.0",
      "rootPassword": "root",
      "database": "devdb",
      "user": "student_grade_system",
      "password": "devpass"
    }
  },
  "forwardPorts": [3306],
  "portsAttributes": {
    "3306": {
      "label": "MySQL",
      "onAutoForward": "notify"
    }
  },
  "remoteUser": "vscode",
  "postCreateCommand": "mysql --version"
}
